py_str_case.py
py_str_case-0.0.4.dist-info/LICENSE
py_str_case-0.0.4.dist-info/METADATA
py_str_case-0.0.4.dist-info/WHEEL
py_str_case-0.0.4.dist-info/top_level.txt
py_str_case-0.0.4.dist-info/RECORD
