Metadata-Version: 2.1
Name: py-str-case
Version: 0.0.4
Summary: String case converter
Home-page: https://github.com/ShivaShankerReddy/py_string_case
Author: shiva
Author-email: shivashanker.chagamreddy@gmail.com
License: UNKNOWN
Platform: UNKNOWN
Classifier: Programming Language :: Python :: 3
Classifier: License :: OSI Approved :: MIT License
Classifier: Operating System :: OS Independent
Requires-Python: >=3.0
